{
  "b_aspirated_to_ai": {
    "count": 2,
    "reason": "could not parse JSON from response"
  },
  "b_aspirated_to_caret": {
    "count": 2,
    "reason": "could not parse JSON from response"
  },
  "b_aspirated_to_o_nas": {
    "count": 1,
    "reason": "could not parse JSON from response"
  },
  "b_aspirated_to_oi": {
    "count": 1,
    "reason": "could not parse JSON from response"
  },
  "b_aspirated_to_schwa": {
    "count": 1,
    "reason": "could not parse JSON from response"
  },
  "b_palatalized_to_a_nas": {
    "count": 1,
    "reason": "could not parse JSON from response"
  },
  "b_palatalized_to_au": {
    "count": 1,
    "reason": "could not parse JSON from response"
  },
  "b_palatalized_to_i": {
    "count": 1,
    "reason": "could not parse JSON from response"
  },
  "b_palatalized_to_i_nas": {
    "count": 1,
    "reason": "could not parse JSON from response"
  },
  "b_palatalized_to_o": {
    "count": 1,
    "reason": "could not parse JSON from response"
  },
  "b_palatalized_to_o_nas": {
    "count": 1,
    "reason": "could not parse JSON from response"
  }
}
