{
  "fromId": "b",
  "toId": "dz",
  "preamble": "The shift from [b] to [dz] is a complex transformation that typically involves a palatalization stage where a labial consonant develops into a dental or alveolar affricate.",
  "phoneticEffects": "Palatalization, Complex Shift.",
  "languageExamples": [
    {
      "language": "Bantu Labial Palatalization",
      "languageFamily": "Bantu",
      "examples": [
        { "from": "[b]", "to": "[dz]", "note": "Stages where labials palatalize to affricates before certain vowels or glides." }
      ]
    }
  ],
  "certainty": 5,
  "commonality": 2,
  "sources": ["Ladefoged, P., & Maddieson, I. (1996). The Sounds of the World's Languages.", "Campbell, L. (2013). Historical Linguistics.", "Schenker, A. M. (1995). The Dawn of Slavic."],
  "tags": ["Palatalization", "Bantu"]
}