{
  "fromId": "b",
  "toId": "p",
  "preamble": "Part of Grimm's Law: PIE voiced plosives became voiceless plosives in Germanic.",
  "phoneticEffects": "Devoicing",
  "languageExamples": [
    {
      "language": "Turkish",
      "languageFamily": "Turkic",
      "examples": [
        { "from": "kitāb [b] (Arabic loanword)", "to": "kitap [p]", "note": "Final consonant devoicing: word-final /b/ → [p] in Turkish (kitap 'book'). In suffixed forms: kitab-ı (ACC), showing underlying /b/." }
      ]
    },
    {
      "language": "PIE to Germanic",
      "languageFamily": "Germanic",
      "examples": [
        {
          "from": "*dheub-",
          "to": "deep (English)",
          "note": "PIE plain voiced *b → PGmc voiceless *p. Cf. Lithuanian dubùs 'hollow, deep' preserving original *b."
        },
        {
          "from": "*slab-",
          "to": "sleep (English)",
          "note": "PIE *b → PGmc *p; PGmc *slēpana- → OE slǣpan → sleep."
        }
      ]
    }
  ],
  "certainty": 5,
  "commonality": 5,
  "sources": [
    "https://en.wikipedia.org/wiki/Grimm%27s_law",
    "Campbell, L. (2013). Historical Linguistics: An Introduction. MIT Press."
  ],
  "tags": [
    "Grimm's Law",
    "Devoicing",
    "Indo-European",
    "Germanic"
  ],
  "period": "Proto-Germanic period",
  "related": [
    {
      "fromId": "d",
      "toId": "t",
      "label": "Grimm's Law (d → t)",
      "type": "chain"
    },
    {
      "fromId": "g",
      "toId": "k",
      "label": "Grimm's Law (g → k)",
      "type": "chain"
    }
  ]
}