{
  "fromId": "caret",
  "toId": "a_nas",
  "preamble": "The shift from the open-mid back unrounded vowel [ʌ] to the nasalized open central unrounded vowel [ã] involves nasalization and fronting.",
  "phoneticEffects": "Nasalization, Fronting",
  "languageExamples": [
    {
      "language": "French (Comparative)",
      "languageFamily": "Romance",
      "examples": [
        { "from": "theoretical [ʌ]", "to": "nasalized [ã]", "note": "In many languages, back or central vowels move forward when nasalized to maximize acoustic distinctiveness." }
      ]
    }
  ],
  "certainty": 5,
  "commonality": 2,
  "sources": [
    "Ladefoged, P. (2001). A Course in Phonetics.",
    "Alkire, T., & Rosen, C. (2010). Romance Philology."
  ],
  "tags": ["Nasalization", "Fronting"]
}
