{
  "fromId": "ch",
  "toId": "ch_retroflex",
  "preamble": "The palato-alveolar affricate [tʃ] merges into the retroflex affricate [ʈʂ] in various Mandarin dialects, contributing to the establishment of the retroflex series.",
  "phoneticEffects": "Merger, Retroflexion, Backing",
  "languageExamples": [
    {
      "language": "Mandarin dialects",
      "languageFamily": "Sino-Tibetan",
      "examples": [
        { "from": "[tʃ]", "to": "[ʈʂ]", "note": "Stabilization of the retroflex series via merger with palato-alveolar sounds." }
      ]
    },
    {
      "language": "Mamean languages (Proto-Mayan)",
      "languageFamily": "Mayan",
      "examples": [
        {
          "from": "Proto-Mayan *tʃ",
          "to": "[ʈʂ] (retroflex affricate)",
          "note": "Part of the Mamean chain shift: Proto-Mayan *[r] > [t], *[t] > [tʃ], *[tʃ] > [ʈʂ], *[ʃ] > [ʂ]. The shift of *tʃ to ʈʂ is well-attested in the Mamean branch (Mam, Tectitec, Awakatec, Ixil) and the resulting retroflex affricates later diffused into neighboring Q'anjob'alan languages through areal contact."
        }
      ]
    }
  ],
  "certainty": 5,
  "commonality": 3,
  "sources": [
    "Norman, J. (1988). Chinese.",
    "Ladefoged, P., & Maddieson, I. (1996). The Sounds of the World's Languages.",
    "Campbell, L. (2013). Historical Linguistics.",
    "https://en.wikipedia.org/wiki/Proto-Mayan_language",
    "https://people.ucsc.edu/~rbennett/resources/papers/pdfs/Bennett%20(2016)%20-%20Mayan%20phonology.pdf"
  ],
  "tags": ["Consonants", "Merger", "Retroflexion", "Mayan", "Sino-Tibetan"]
}