{
  "fromId": "d",
  "toId": "ch",
  "preamble": "The shift from the voiced alveolar stop [d] to the voiceless palato-alveolar affricate [tʃ] involves three steps: palatalization (due to a following [i] or [j]), affrication, and finally devoicing. It is often seen in rapid speech or as a historical progression of 'yod-coalescence'.",
  "phoneticEffects": "Affrication, Devoicing, Yod-coalescence",
  "languageExamples": [
    {
      "language": "English",
      "languageFamily": "Germanic",
      "examples": [
        {
          "from": "[d] before [j]",
          "to": "[tʃ]",
          "note": "Yod-coalescence merges [d] + [j] through intermediate affrication ([dʒ]) and devoicing to [tʃ]."
        }
      ]
    }
  ],
  "certainty": 4,
  "commonality": 3,
  "sources": [
    "https://www.cambridge.org/core/books/accents-of-english/A9495FCF7CC13D1D11FADB3DE2F335F6",
    "https://en.wikipedia.org/wiki/Phonological_history_of_English_consonants#Yod-coalescence"
  ],
  "tags": [
    "Affrication",
    "Devoicing",
    "Yod-coalescence"
  ],
  "related": [
    { "fromId": "t", "toId": "ch", "label": "Voiceless equivalent: Palatalization", "type": "branch" }
  ]
}
