{
  "fromId": "dz",
  "toId": "d_palatal",
  "preamble": "Shift of a voiced alveolar affricate to a voiced palatal stop.",
  "phoneticEffects": "Palatalization, De-assibilation",
  "languageExamples": [
    {
      "language": "Dialectal variations",
      "languageFamily": "various",
      "examples": [
        { "from": "[dz]", "to": "[ɟ]", "note": "Development where voiced affricates are realized as voiced palatal stops." }
      ]
    }
  ],
  "certainty": 5,
  "commonality": 2,
  "sources": [
    "Ladefoged, P., & Maddieson, I. (1996). The Sounds of the World's Languages.",
    "Campbell, L. (2013). Historical Linguistics."
  ],
  "tags": ["Palatalization", "De-assibilation"]
}