{
  "fromId": "dz",
  "toId": "d",
  "preamble": "Deaffrication. The voiced alveolar affricate [dz] simplifies to a simple voiced alveolar stop [d], losing its fricative release. This process occurred during various historical stages in Slavic and Romance languages.",
  "phoneticEffects": "Deaffrication",
  "languageExamples": [
    {
      "language": "Slavic Languages",
      "languageFamily": "Indo-European",
      "examples": [
        { "from": "dz", "to": "d", "note": "Historical deaffrication in various Slavic branches." }
      ]
    },
    {
      "language": "Romance Languages",
      "languageFamily": "Indo-European",
      "examples": [
        { "from": "dz", "to": "d", "note": "Occurred during the evolution from Vulgar Latin." }
      ]
    }
  ],
  "certainty": 5,
  "commonality": 3,
  "sources": [
    "Ladefoged, P., & Maddieson, I. (1996). The Sounds of the World's Languages.",
    "Campbell, L. (2013). Historical Linguistics."
  ],
  "tags": ["Deaffrication"]
}
