{
  "fromId": "e",
  "toId": "i",
  "preamble": "The shift from the mid front vowel [e] to the high front vowel [i] is a process of Vowel Raising. This can occur as a regular sound change in stressed syllables, part of a chain shift, or as a reduction process in unstressed syllables.",
  "phoneticEffects": "Vowel Raising",
  "languageExamples": [
    {
      "language": "English (Great Vowel Shift)",
      "languageFamily": "Germanic",
      "examples": [
        {
          "from": "take [teːkə]",
          "to": "[tiːk] > [teɪk]",
          "note": "Middle English long /e:/ raised to /i:/ as part of the Great Vowel Shift (later diphthongizing in many words)."
        },
        {
          "from": "meet [meːtə]",
          "to": "meet [miːt]",
          "note": "Long /e:/ regularly raised to /i:/."
        }
      ]
    },
    {
      "language": "Latin to Romance",
      "languageFamily": "Romance",
      "examples": [
        {
          "from": "fēcī (Latin)",
          "to": "hice (Spanish)",
          "note": "Raising of /e:/ to /i/ in some Romance verb forms."
        }
      ]
    },
    {
      "language": "Russian (Ikanie)",
      "languageFamily": "East Slavic",
      "examples": [
        {
          "from": "ре́ка [rʲe-] (stressed)",
          "to": "река́ [rʲɪ-] (unstressed)",
          "note": "Unstressed /e/ reduces and raises towards [i] (phonetically [ɪ]) in Russian."
        }
      ]
    },
    {
      "language": "Cholan languages (Proto-Mayan)",
      "languageFamily": "Mayan",
      "examples": [
        {
          "from": "Proto-Mayan *eː (long close-mid front vowel)",
          "to": "i",
          "note": "All Cholan languages (Ch'ol, Ch'orti', Chontal) raised Proto-Mayan long *eː to short /i/. This is one of two parallel raising changes in Cholan (the other being *oː > u), eliminating vowel length in the branch. The change is well-documented in Kaufman and Norman's Proto-Cholan reconstruction and is diagnostic for Cholan membership."
        }
      ]
    }
  ],
  "certainty": 5,
  "commonality": 5,
  "sources": [
    "Campbell, L. (2013). Historical Linguistics: An Introduction.",
    "Ladefoged, P. (2001). A Course in Phonetics.",
    "Alkire, T., & Rosen, C. (2010). Romance Languages: A Historical Introduction. Cambridge University Press.",
    "https://en.wikipedia.org/wiki/Proto-Mayan_language",
    "Kaufman, T. & Norman, W. (1984). An Outline of Proto-Cholan Phonology, Morphology and Vocabulary. In Munro Edmonson (ed.), Phoneticism in Mayan Hieroglyphic Writing."
  ],
  "tags": [
    "Raising",
    "Germanic",
    "Romance",
    "Slavic",
    "Mayan"
  ]
}