{
  "fromId": "empty",
  "toId": "e",
  "preamble": "Prothesis of [e] is a defining feature of Western Romance languages, where the vowel was added before Latin words starting with 's-impurum' (s + consonant).",
  "phoneticEffects": "Prothesis",
  "languageExamples": [
    {
      "language": "Spanish",
      "languageFamily": "Romance",
      "examples": [
        { "from": "status", "to": "estado", "note": "from Latin" },
        { "from": "scola", "to": "escuela", "note": "from Latin" }
      ]
    },
    {
      "language": "French",
      "languageFamily": "Romance",
      "examples": [
        { "from": "spiritus", "to": "esprit", "note": "from Latin" }
      ]
    }
  ],
  "certainty": 5,
  "commonality": 5,
  "sources": [
    "https://www.cambridge.org/core/books/history-of-the-spanish-language/03501B0EC536AC346B59BFAF6BC5E89E"
  ],
  "tags": ["Prothesis", "Romance"],
  "period": "Vulgar Latin period",
  "related": [
    { "fromId": "e", "toId": "empty", "label": "Deletion", "type": "branch" }
  ]
}