{
  "fromId": "g_aspirated",
  "toId": "j_glide",
  "preamble": "The shift from the voiced aspirated velar stop [ɡʱ] to the palatal approximant [j] is a form of palatalization and lenition. This weakening often occurs before front vowels where the velar closure is pulled forward and eventually reduced to a glide.",
  "phoneticEffects": "Palatalization, Lenition",
  "languageExamples": [
    {
      "language": "Old English (Historical)",
      "languageFamily": "Germanic",
      "examples": [
        { "from": "historical *ɡ (from PIE *ɡʱ)", "to": "[j]", "note": "PIE *ɡʱel- > PGmc *gastiz > OE 'geolu' [j], leading to Modern English 'yellow'." }
      ]
    }
  ],
  "certainty": 5,
  "commonality": 3,
  "sources": [
    "Lass, R. (1997). Historical Linguistics and Language Change.",
    "Hock, H. H. (1991). Principles of Historical Linguistics."
  ],
  "tags": ["Palatalization", "Lenition", "Germanic"],
  "related": [
    { "fromId": "g_aspirated", "toId": "gamma", "label": "Intermediate spirantization", "type": "chain" }
  ]
}