{
  "fromId": "j_palatal",
  "toId": "zh_retroflex",
  "preamble": "The transformation of a voiced alveolo-palatal affricate [dʑ] into a voiced retroflex fricative [ʐ].",
  "phoneticEffects": "Deaffrication, Retraction",
  "languageExamples": [
    {
      "language": "Mandarin",
      "languageFamily": "Sino-Tibetan",
      "examples": [
        {
          "from": "[dʑ]",
          "to": "[ʐ]",
          "note": "Development of the Mandarin 'r' sound from earlier palatal sources."
        }
      ]
    }
  ],
  "certainty": 4,
  "commonality": 2,
  "sources": [
    "Norman, J. (1988). Chinese.",
    "Baxter, W. H. (1992). A Handbook of Old Chinese Phonology."
  ],
  "tags": ["Deaffrication", "Retraction", "Sino-Tibetan"]
}
