{
  "fromId": "o",
  "toId": "ui",
  "preamble": "The transformation of the close-mid back rounded vowel /o/ into the diphthong /ui/ involves a complex series of phonetic changes. This shift typically includes raising of the vowel, fronting from a back to a front position, and diphthongization from a monophthong to a gliding vowel sound. Additionally, the process often entails unrounding, particularly in the final element of the diphthong.",
  "phoneticEffects": "Raising, Fronting, Diphthongization, Unrounding",
  "languageExamples": [
    {
      "language": "Rampurhat Variety of Bangla",
      "languageFamily": "Indo-Aryan",
      "examples": [
        {
          "from": "/o/",
          "to": "/ui/",
          "note": "as part of the word /nit̪t̪o/ 'regularly' becoming /lit̪ui/"
        }
      ]
    }
  ],
  "certainty": 4,
  "commonality": 3,
  "sources": [
    "Chatterjee, S. (2022). Phonological Analysis of Rampurhat Variety of Bangla. Language in India, 22(3), 95-108."
  ],
  "tags": [
    "Diphthongization",
    "Vowel Shift",
    "Raising",
    "Fronting",
    "Unrounding",
    "Indo-Aryan"
  ],
  "related": [
    {
      "fromId": "ui",
      "toId": "o",
      "label": "Reverse",
      "type": "branch"
    }
  ]
}
