{
  "fromId": "s",
  "toId": "h",
  "preamble": "The debuccalization of the voiceless alveolar sibilant /s/ into a glottal fricative /h/, a common process of phonetic weakening found across many language families.",
  "phoneticEffects": "Debuccalization, Aspiration",
  "languageExamples": [
    {
      "language": "Proto-Malayo-Polynesian",
      "languageFamily": "Austronesian",
      "examples": [
        { "from": "*Sikan (PAN 'fish')", "to": "ikan [h→∅] (Indonesian)", "note": "PAN *S → PMP *h (then → ∅ in Malay/Indonesian). Cf. Tagalog 'isda' and Malay 'ikan' reflecting different outcomes of *S." }
      ]
    },
    {
      "language": "Ancient Greek",
      "languageFamily": "Indo-European",
      "examples": [
        { "from": "*septm", "to": "hepta", "note": "Initial PIE *s became /h/ in Greek." }
      ]
    },
    {
      "language": "Spanish (Andalusian/Caribbean)",
      "languageFamily": "Romance",
      "examples": [
        { "from": "esta", "to": "[ˈehta]", "note": "Syllable-final /s/ debuccalization." }
      ]
    }
  ],
  "certainty": 5,
  "commonality": 5,
  "sources": ["Penny, R. (2002). A History of the Spanish Language.", "Sihler, A. L. (1995). New Comparative Grammar of Greek and Latin."],
  "tags": ["Debuccalization", "Greek", "Spanish"],
  "related": [
    { "fromId": "h", "toId": "s", "label": "Fortition", "type": "branch" }
  ]
}