{
  "fromId": "th_vced",
  "toId": "n",
  "preamble": "The voiced dental fricative /ð/ can undergo a phonetic transformation to the alveolar nasal /n/, primarily through processes of assimilation in connected speech. This shift involves a change in the manner of articulation from a fricative to a nasal, and a slight adjustment in the place of articulation from dental to alveolar.",
  "phoneticEffects": "Manner assimilation, place assimilation, nasalization",
  "languageExamples": [
    {
      "language": "Old Icelandic",
      "languageFamily": "North Germanic",
      "examples": [
        {
          "from": "/gunð-a/",
          "to": "/gunna/",
          "note": "Assimilation of /ð/ to /n/ when between a preceding /n/ and a vowel."
        }
      ]
    },
    {
      "language": "English",
      "languageFamily": "Germanic",
      "examples": [
        {
          "from": "/wɒznt ðɛər/",
          "to": "/wɒnnt nɛər/",
          "note": "Progressive manner assimilation of /ð/ to a preceding /n/ in rapid speech, as in 'wasn't there'."
        },
        {
          "from": "/wɪn ðə reɪs/",
          "to": "/wɪn nə reɪs/",
          "note": "Progressive manner assimilation of /ð/ to a preceding /n/ in rapid speech, as in 'win the race'."
        }
      ]
    },
    {
      "language": "African American English",
      "languageFamily": "Germanic",
      "examples": [
        {
          "from": "/ðæn/",
          "to": "[næn]",
          "note": "A broader change of initial /ð/ to [n] in some phonological contexts, as in 'than'."
        }
      ]
    }
  ],
  "certainty": 5,
  "commonality": 3,
  "sources": [
    "Jones, J. (2023). African American English intensifier dennamug: Using twitter to investigate syntactic change in low-frequency forms. Frontiers in Communication, 8."
  ],
  "tags": [
    "Assimilation",
    "Nasalization",
    "Germanic",
    "Historical Linguistics",
    "Phonetics"
  ],
  "related": [
    {
      "fromId": "n",
      "toId": "th_vced",
      "label": "Reverse",
      "type": "branch"
    }
  ]
}
