{
  "fromId": "ts",
  "toId": "l",
  "preamble": "The transformation of the voiceless alveolar affricate /ts/ to the alveolar lateral approximant /l/ is a documented phonetic shift, observed as a form of lenition where a more complex obstruent simplifies to a sonorant.",
  "phoneticEffects": "Lenition, simplification of affricate to approximant, change in manner of articulation from affricate to lateral approximant",
  "languageExamples": [
    {
      "language": "Sesotho",
      "languageFamily": "Bantu",
      "examples": [
        {
          "from": "/ts/",
          "to": "/l/",
          "note": "A common phonetic change in the Sotho-Tswana group of languages, where /ts/ can shift to /l/ or /d/."
        }
      ]
    }
  ],
  "certainty": 4,
  "commonality": 5,
  "sources": [
    "Sesotho language - Academic Kids."
  ],
  "tags": [
    "Lenition",
    "Affricate",
    "Approximant",
    "Bantu"
  ]
}
