{
  "fromId": "u",
  "toId": "e",
  "preamble": "The shift from the high back rounded vowel [u] to the mid front unrounded vowel [e] is a complex process involving fronting and lowering, often occurring as part of a vowel chain shift or through an intermediate rounded front vowel [y].",
  "phoneticEffects": "Fronting, Lowering, Vowel Shift",
  "languageExamples": [
    {
      "language": "Yiddish (from Middle High German)",
      "languageFamily": "Germanic",
      "examples": [
        {
          "from": "MHG grüss [yː] (greeting)",
          "to": "Yiddish grus/gres [e]",
          "note": "Some MHG ü/y forms appear with /e/ reflex in certain Yiddish dialects; the front rounded ü unrounded via intermediate stages to e or i depending on dialect and phonetic context."
        }
      ]
    },
    {
      "language": "Scandinavian Dialects",
      "languageFamily": "Indo-European (North Germanic)",
      "examples": [
        {
          "from": "[u]",
          "to": "[e]",
          "note": "Historical fronting to [y] followed by lowering and unrounding to [e] in specific regional varieties."
        }
      ]
    },
    {
      "language": "Middle English to Modern English",
      "languageFamily": "Indo-European (Germanic)",
      "examples": [
        {
          "from": "Historical [uː]",
          "to": "[eɪ]",
          "note": "Part of the Great Vowel Shift chain where high vowels diphthongized and interacted with fronted reflexes."
        }
      ]
    }
  ],
  "certainty": 3,
  "commonality": 2,
  "sources": [
    "https://en.wikipedia.org/wiki/Great_Vowel_Shift",
    "https://en.wikipedia.org/wiki/Vowel_shift"
  ],
  "tags": [
    "Fronting",
    "Lowering",
    "Chain-Shift",
    "Germanic"
  ],
  "related": [
    {
      "fromId": "u",
      "toId": "i",
      "label": "Iotacism",
      "type": "chain"
    },
    {
      "fromId": "o",
      "toId": "e",
      "label": "Fronting/Lowering",
      "type": "branch"
    }
  ]
}
