{
  "fromId": "uo",
  "toId": "i",
  "preamble": "Monophthongization of the diphthong [uo] to the close front unrounded vowel [i] through vowel merger and raising. This shift occurs in various Sino-Tibetan and Romance languages, representing a pathway toward high vowel targets in diphthong reduction.",
  "phoneticEffects": "Monophthongization, Raising, Fronting",
  "languageExamples": [
    {
      "language": "Wu Chinese (contemporary)",
      "languageFamily": "Sino-Tibetan",
      "examples": [
        {
          "from": "[uo]",
          "to": "[i]",
          "note": "In Wu Chinese dialects, the diphthong [uo] monophthongizes to close front vowel [i] in certain phonological contexts."
        }
      ]
    },
    {
      "language": "Romance languages (dialectal)",
      "languageFamily": "Romance",
      "examples": [
        {
          "from": "[uo]",
          "to": "[i]",
          "note": "In some Romance dialects, [uo] reduces to high vowel [i] in rapid speech, particularly before certain consonants."
        }
      ]
    }
  ],
  "certainty": 1,
  "commonality": 1,
  "sources": [
    "https://en.wikipedia.org/wiki/Monophthongization",
    "https://en.wikipedia.org/wiki/Wu_Chinese"
  ],
  "tags": [
    "Monophthongization",
    "Raising",
    "Romance",
    "Sino-Tibetan"
  ],
  "related": [
    {
      "fromId": "uo_to_a",
      "toId": "uo_to_i",
      "label": "Alternative monophthongization target",
      "type": "branch"
    }
  ]
}
